pmxbot.saysomething-1.0.0-py3.6-nspkg.pth
pmxbot/saysomething.py
pmxbot.saysomething-1.0.0.dist-info/DESCRIPTION.rst
pmxbot.saysomething-1.0.0.dist-info/LICENSE.txt
pmxbot.saysomething-1.0.0.dist-info/METADATA
pmxbot.saysomething-1.0.0.dist-info/RECORD
pmxbot.saysomething-1.0.0.dist-info/WHEEL
pmxbot.saysomething-1.0.0.dist-info/entry_points.txt
pmxbot.saysomething-1.0.0.dist-info/metadata.json
pmxbot.saysomething-1.0.0.dist-info/namespace_packages.txt
pmxbot.saysomething-1.0.0.dist-info/top_level.txt
