Metadata-Version: 2.0
Name: pmxbot.saysomething
Version: 1.0.0
Summary: Markov chain phrase generator for pmxbot
Home-page: https://github.com/yougov/pmxbot.saysomething
Author: Jason R. Coombs
Author-email: jaraco@jaraco.com
License: UNKNOWN
Platform: UNKNOWN
Classifier: Development Status :: 5 - Production/Stable
Classifier: Intended Audience :: Developers
Classifier: License :: OSI Approved :: MIT License
Classifier: Programming Language :: Python :: 3
Requires-Python: >=3.4
Requires-Dist: more-itertools
Requires-Dist: jaraco.collections
Requires-Dist: jaraco.mongodb
Provides-Extra: docs
Requires-Dist: sphinx; extra == 'docs'
Requires-Dist: jaraco.packaging (>=3.2); extra == 'docs'
Requires-Dist: rst.linker (>=1.9); extra == 'docs'
Provides-Extra: testing
Requires-Dist: pytest (>=2.8); extra == 'testing'
Requires-Dist: pytest-sugar; extra == 'testing'
Requires-Dist: collective.checkdocs; extra == 'testing'
Requires-Dist: pmxbot (>=1121); extra == 'testing'
